pydumpling-0.1.6.dist-info/METADATA
pydumpling-0.1.6.dist-info/WHEEL
pydumpling-0.1.6.dist-info/licenses/LICENSE
pydumpling/__init__.py
pydumpling/__main__.py
pydumpling/cli.py
pydumpling/debug_dumpling.py
pydumpling/fake_types.py
pydumpling/helpers.py
pydumpling/pydumpling.py
pydumpling/rpdb.py
pydumpling-0.1.6.dist-info/RECORD
