Metadata-Version: 2.1
Name: pydumpling
Version: 0.1.6
Summary: Python post-mortem debugger
Home-page: https://github.com/cocolato/pydumpling
Author-Email: cocolato <haiizhu@outlook.com>
License: MIT
Project-URL: Homepage, https://github.com/cocolato/pydumpling
Requires-Python: >=3.7
Requires-Dist: dill<1.0.0,>=0.3.2
Requires-Dist: packaging>=24.0
Requires-Dist: sphinx>=4.3.2; extra == "doc"
Requires-Dist: sphinx-rtd-theme>=1.3.0; extra == "doc"
Requires-Dist: sphinx-tabs>=3.4.5; extra == "doc"
Requires-Dist: sphinx-copybutton>=0.5.2; extra == "doc"
Provides-Extra: doc
